{
    "nameRus": "Бека",
    "nameEng": "beckanx",
    "about": "<b>Шкала тревоги Бека</b> (англ. <i>The Beck Anxiety Inventory</i>, сокр. BAI) — клиническая тестовая методика, предназначенная для скрининга тревоги и оценки степени её выраженности. Опросник состоит из 21 пункта.\n\nОтметьте, насколько вас беспокоил каждый из этих симптомов в течение <b>последней недели</b>.",
    "questions": [
        "Ощущение онемения или покалывания в теле",
        "Ощущение жары",
        "Дрожь в ногах",
        "Неспособность расслабиться",
        "Страх, что произойдет самое плохое",
        "Головокружение или ощущение легкости в голове",
        "Ускоренное сердцебиение",
        "Неустойчивость",
        "Ощущение ужаса",
        "Нервозность",
        "Дрожь в руках",
        "Ощущение удушья",
        "Шаткость походки",
        "Страх утраты контроля",
        "Затрудненность дыхания",
        "Страх смерти",
        "Испуг",
        "Желудочно-кишечные расстройства",
        "Обмороки",
        "Приливы крови к лицу",
        "Усиление потоотделения (не связанное с жарой)"
        ],
    "pointText": 
        [
            "Совсем не беспокоил",
            "Слегка. Не слишком меня беспокоил",
	        "Умеренно. Это было неприятно, но я мог это переносить",
	        "Очень сильно. Я с трудом мог это выносить"
        ],
    "pointInt": [0, 1, 2, 3],
    "resultText": 
    [
        "Незначительный уровнь тревоги.",
	    "Средняя выраженность тревоги.",
	    "Сильная тревога."
    ],
    "resultSum": [21, 35, 63]
}